kipris_api_wrapper/__init__.py
kipris_api_wrapper/client.py
kipris_api_wrapper/config.py
kipris_api_wrapper/exceptions.py
kipris_api_wrapper/models.py
kipris_api_wrapper/trademark_asign_product_search_info.py
kipris_api_wrapper/trademark_get_advanced_search.py
kipris_api_wrapper/utils.py
kipris_api_wrapper/core/__init__.py
kipris_api_wrapper/core/_request_helpers.py
kipris_api_wrapper/core/auth.py
kipris_api_wrapper-0.1.0.dist-info/licenses/LICENSE
kipris_api_wrapper-0.1.0.dist-info/METADATA
kipris_api_wrapper-0.1.0.dist-info/WHEEL
kipris_api_wrapper-0.1.0.dist-info/top_level.txt
kipris_api_wrapper-0.1.0.dist-info/RECORD
