Metadata-Version: 2.4
Name: kipris-api-wrapper
Version: 0.1.0
Summary: Python wrapper for KIPRIS Open API
Author-email: Song <song@songohip.com>
License: MIT
Project-URL: Homepage, https://github.com/patentsong/songohip.git
Project-URL: Repository, https://github.com/patentsong/songohip.git
Keywords: kipris,api,patent,trademark,intellectual property
Requires-Python: ~=3.12
License-File: LICENSE
Requires-Dist: httpx>=0.28.1
Requires-Dist: lxml>=5.4.0
Requires-Dist: pydantic>=2.10.1
Provides-Extra: dev
Requires-Dist: pytest>=8.0; extra == "dev"
Requires-Dist: pytest-asyncio>=0.23.0; extra == "dev"
Requires-Dist: pytest-mock>=3.14.0; extra == "dev"
Requires-Dist: coverage>=7.8.0; extra == "dev"
Requires-Dist: pytest-cov>=5.0.0; extra == "dev"
Requires-Dist: python-dotenv>=1.0.0; extra == "dev"
Requires-Dist: build; extra == "dev"
Provides-Extra: local
Requires-Dist: python-dotenv>=1.0.0; extra == "local"
Provides-Extra: gcp
Requires-Dist: google-cloud-secret-manager; extra == "gcp"
Dynamic: license-file
